wagtailgeowidget/__init__.py
wagtailgeowidget/app_settings.py
wagtailgeowidget/apps.py
wagtailgeowidget/blocks.py
wagtailgeowidget/geocoders.py
wagtailgeowidget/helpers.py
wagtailgeowidget/panels.py
wagtailgeowidget/widgets.py
wagtailgeowidget/locale/en/LC_MESSAGES/django.po
wagtailgeowidget/locale/fr/LC_MESSAGES/django.po
wagtailgeowidget/locale/sv/LC_MESSAGES/django.po
wagtailgeowidget/migrations/__init__.py
wagtailgeowidget/static/wagtailgeowidget/css/google-maps-field.css
wagtailgeowidget/static/wagtailgeowidget/css/leaflet-field.css
wagtailgeowidget/static/wagtailgeowidget/js/geocoder-field-controller.js
wagtailgeowidget/static/wagtailgeowidget/js/geocoder-field-telepath.js
wagtailgeowidget/static/wagtailgeowidget/js/geocoder-field.js
wagtailgeowidget/static/wagtailgeowidget/js/google-maps-field-controller.js
wagtailgeowidget/static/wagtailgeowidget/js/google-maps-field-telepath.js
wagtailgeowidget/static/wagtailgeowidget/js/google-maps-field.js
wagtailgeowidget/static/wagtailgeowidget/js/leaflet-field-controller.js
wagtailgeowidget/static/wagtailgeowidget/js/leaflet-field-telepath.js
wagtailgeowidget/static/wagtailgeowidget/js/leaflet-field.js
wagtailgeowidget-9.1.0.dist-info/licenses/LICENSE
wagtailgeowidget-9.1.0.dist-info/METADATA
wagtailgeowidget-9.1.0.dist-info/WHEEL
wagtailgeowidget-9.1.0.dist-info/top_level.txt
wagtailgeowidget-9.1.0.dist-info/RECORD
